python_lang/__init__.py
python_lang-1.0.0.dist-info/LICENSE
python_lang-1.0.0.dist-info/METADATA
python_lang-1.0.0.dist-info/WHEEL
python_lang-1.0.0.dist-info/top_level.txt
python_lang-1.0.0.dist-info/RECORD
