Metadata-Version: 2.1
Name: python-lang
Version: 1.0.0
Summary: A simple library for building multilingual applications in Python
Home-page: https://github.com/Programista3/python-lang
Author: Grzegorz Babiarz
Author-email: programista3@outlook.com
License: UNKNOWN
Platform: UNKNOWN
Classifier: Programming Language :: Python :: 3
Classifier: License :: OSI Approved :: MIT License
Classifier: Operating System :: OS Independent
